Metadata-Version: 2.1
Name: pyGinit
Version: 0.2.9
Summary: a simple cli tools for automation git repository creation
Home-page: https://github.com/AlphaBeta1906/pyGinit
Author: fariz
Author-email: farizi1906@gmail.com
License: MIT
Download-URL: https://github.com/AlphaBeta1906/pyGinit/archive/refs/tags/v0.2.9.tar.gz
Keywords: automation,tools,cli,git,github,development
Platform: UNKNOWN
Classifier: Development Status :: 5 - Production/Stable
Classifier: Intended Audience :: Developers
Classifier: License :: OSI Approved :: MIT License
Classifier: Environment :: Console
Classifier: Programming Language :: Python :: 3.7
Classifier: Programming Language :: Python :: 3.8
Classifier: Programming Language :: Python :: 3.9
Classifier: Programming Language :: Python :: 3 :: Only
Requires-Python: >=3.7
